{
  "center_letter": "T",
  "outer_letters": [
    "A",
    "C",
    "I",
    "K",
    "L",
    "O"
  ],
  "answers": [
    "cocktail",
    "alit",
    "allot",
    "alto",
    "atilt",
    "atoll",
    "attack",
    "attic",
    "cacti",
    "catcall",
    "cattail",
    "clot",
    "coat",
    "coati",
    "coattail",
    "cockatoo",
    "coital",
    "colt",
    "coot",
    "illicit",
    "iota",
    "italic",
    "kilt",
    "lactic",
    "licit",
    "lilt",
    "loot",
    "lotto",
    "octal",
    "tacit",
    "tack",
    "taco",
    "tact",
    "tactic",
    "tactical",
    "tail",
    "tailcoat",
    "talc",
    "tali",
    "talk",
    "tall",
    "tallit",
    "tattoo",
    "tick",
    "ticktock",
    "tiki",
    "tikka",
    "till",
    "tilt",
    "toccata",
    "tock",
    "toil",
    "toll",
    "took",
    "tool",
    "toolkit",
    "toot",
    "total"
  ],
  "pangrams": [
    "cocktail"
  ],
  "Beginner": 0,
  "Good Start": 4,
  "Moving Up": 11,
  "Good": 18,
  "Solid": 33,
  "Nice": 55,
  "Great": 88,
  "Amazing": 110,
  "Genius": 154,
  "Queen Bee": 220
}