{
  "center_letter": "L",
  "outer_letters": [
    "A",
    "C",
    "D",
    "I",
    "R",
    "Y"
  ],
  "answers": [
    "acridly",
    "radically",
    "acidly",
    "acrylic",
    "acyclic",
    "airily",
    "allay",
    "ally",
    "aril",
    "call",
    "calla",
    "carryall",
    "cilia",
    "clad",
    "clay",
    "cyclic",
    "cyclical",
    "cyclically",
    "daily",
    "dally",
    "daylily",
    "dial",
    "diddly",
    "dill",
    "dilly",
    "dillydally",
    "drill",
    "dryly",
    "icily",
    "idly",
    "idyl",
    "idyll",
    "idyllic",
    "idyllically",
    "iliac",
    "illy",
    "lacy",
    "lady",
    "laic",
    "laical",
    "laid",
    "lair",
    "lard",
    "liar",
    "lilac",
    "lily",
    "lira",
    "lyric",
    "lyrical",
    "lyrically",
    "racial",
    "racially",
    "racily",
    "radial",
    "radially",
    "radical",
    "rail",
    "railcar",
    "rally",
    "rial",
    "rill",
    "riyal"
  ],
  "pangrams": [
    "acridly",
    "radically"
  ],
  "Beginner": 0,
  "Good Start": 6,
  "Moving Up": 15,
  "Good": 24,
  "Solid": 44,
  "Nice": 74,
  "Great": 118,
  "Amazing": 148,
  "Genius": 207,
  "Queen Bee": 296
}