{
  "center_letter": "P",
  "outer_letters": [
    "G",
    "I",
    "L",
    "N",
    "T",
    "Y"
  ],
  "answers": [
    "pityingly",
    "lipping",
    "lippy",
    "nipping",
    "nippy",
    "pigging",
    "piggy",
    "piling",
    "pill",
    "pilling",
    "ping",
    "pinging",
    "pining",
    "pinning",
    "pinny",
    "pint",
    "piping",
    "pipit",
    "pippin",
    "pitting",
    "pity",
    "pitying",
    "plying",
    "tipi",
    "tipping",
    "tippling",
    "tippy",
    "typing",
    "yipping"
  ],
  "pangrams": [
    "pityingly"
  ],
  "Beginner": 0,
  "Good Start": 3,
  "Moving Up": 8,
  "Good": 13,
  "Solid": 25,
  "Nice": 41,
  "Great": 66,
  "Amazing": 83,
  "Genius": 115,
  "Queen Bee": 165
}