{
  "center_letter": "E",
  "outer_letters": [
    "G",
    "I",
    "N",
    "T",
    "U",
    "Y"
  ],
  "answers": [
    "ingenuity",
    "egging",
    "eggy",
    "engine",
    "ennui",
    "entente",
    "entity",
    "eyeing",
    "eying",
    "gene",
    "genie",
    "genii",
    "gent",
    "genuine",
    "getting",
    "gigue",
    "ignite",
    "ingenue",
    "innie",
    "intent",
    "nene",
    "netting",
    "netty",
    "nine",
    "nineteen",
    "ninety",
    "nite",
    "nugget",
    "teeing",
    "teen",
    "teeny",
    "tenet",
    "tent",
    "tenting",
    "tenuity",
    "tine",
    "tinge",
    "tingeing",
    "tune",
    "tutee",
    "unguent",
    "unite",
    "untie",
    "untune",
    "yenning",
    "yente",
    "yeti"
  ],
  "pangrams": [
    "ingenuity"
  ],
  "Beginner": 0,
  "Good Start": 5,
  "Moving Up": 12,
  "Good": 19,
  "Solid": 35,
  "Nice": 59,
  "Great": 94,
  "Amazing": 118,
  "Genius": 165,
  "Queen Bee": 236
}