{
  "center_letter": "L",
  "outer_letters": [
    "C",
    "E",
    "I",
    "M",
    "N",
    "Y"
  ],
  "answers": [
    "inclemency",
    "cell",
    "celli",
    "cicely",
    "clemency",
    "clime",
    "clinic",
    "cycle",
    "cyclic",
    "eely",
    "icicle",
    "icily",
    "illy",
    "incline",
    "lenience",
    "leniency",
    "lice",
    "lien",
    "lily",
    "lime",
    "limn",
    "line",
    "linemen",
    "linen",
    "melee",
    "mile",
    "mill",
    "myelin",
    "nicely",
    "yell"
  ],
  "pangrams": [
    "inclemency"
  ],
  "Beginner": 0,
  "Good Start": 3,
  "Moving Up": 7,
  "Good": 11,
  "Solid": 20,
  "Nice": 33,
  "Great": 53,
  "Amazing": 67,
  "Genius": 93,
  "Queen Bee": 133
}